dataknead/__init__.py
dataknead/baseloader.py
dataknead/console.py
dataknead/knead.py
dataknead/loaders/__init__.py
dataknead/loaders/csv.py
dataknead/loaders/excel.py
dataknead/loaders/json.py
dataknead/loaders/text.py
dataknead/loaders/toml.py
dataknead/loaders/util.py
dataknead/loaders/xml.py
dataknead-0.4.0.dist-info/entry_points.txt
dataknead-0.4.0.dist-info/LICENSE.txt
dataknead-0.4.0.dist-info/WHEEL
dataknead-0.4.0.dist-info/METADATA
dataknead-0.4.0.dist-info/RECORD
